{"cik":1843351,"entityName":"Kadem Sustainable Impact Corp","facts":{"us-gaap":{"AccountsPayableCurrent":{"label":"Accounts Payable, Current","description":"Carrying value as of the balance sheet date of liabilities incurred (and for which invoices have typically been received) and payable to vendors for goods and services received that are used in an entity's business. Used to reflect the current portion of the liabilities (due within one year or within the normal operating cycle if longer).","units":{"USD":[{"end":"2020-12-31","val":0,"accn":"0001193125-21-173844","fy":2021,"fp":"Q1","form":"10-Q/A","filed":"2021-05-27"},{"end":"2020-12-31","val":0,"accn":"0001193125-21-247908","fy":2021,"fp":"Q2","form":"10-Q","filed":"2021-08-16"},{"end":"2020-12-31","val":0,"accn":"0001193125-21-334994","fy":2021,"fp":"Q3","form":"10-Q","filed":"2021-11-19","frame":"CY2020Q4I"},{"end":"2021-03-31","val":121622,"accn":"0001193125-21-173844","fy":2021,"fp":"Q1","form":"10-Q/A","filed":"2021-05-27","frame":"CY2021Q1I"},{"end":"2021-06-30","val":7309,"accn":"0001193125-21-247908","fy":2021,"fp":"Q2","form":"10-Q","filed":"2021-08-16","frame":"CY2021Q2I"},{"end":"2021-09-30","val":46118,"accn":"0001193125-21-334994","fy":2021,"fp":"Q3","form":"10-Q","filed":"2021-11-19","frame":"CY2021Q3I"}]}},"AccountsPayableOtherCurrent":{"label":"Accounts Payable, Other, Current","description":"Amount of obligations incurred classified as other, payable within one year or the normal operating cycle, if longer.","units":{"USD":[{"end":"2021-03-19","val":13360,"accn":"0001193125-21-173844","fy":2021,"fp":"Q1","form":"10-Q/A","filed":"2021-05-27","frame":"CY2021Q1I"}]}},"AccrualForTaxesOtherThanIncomeTaxesCurrent":{"label":"Accrual for Taxes Other than Income Taxes, Current","description":"Carrying value as of the balance sheet date of obligations incurred and payable for real and property taxes. Used to reflect the current portion of the liabilities (due within one year or within the normal operating cycle if longer).","units":{"USD":[{"end":"2020-12-31","val":0,"accn":"0001193125-21-247908","fy":2021,"fp":"Q2","form":"10-Q","filed":"2021-08-16"},{"end":"2020-12-31","val":0,"accn":"0001193125-21-334994","fy":2021,"fp":"Q3","form":"10-Q","filed":"2021-11-19","frame":"CY2020Q4I"},{"end":"2021-06-30","val":100000,"accn":"0001193125-21-247908","fy":2021,"fp":"Q2","form":"10-Q","filed":"2021-08-16","frame":"CY2021Q2I"},{"end":"2021-09-30","val":150000,"accn":"0001193125-21-334994","fy":2021,"fp":"Q3","form":"10-Q","filed":"2021-11-19","frame":"CY2021Q3I"}]}},"AccruedLiabilitiesCurrent":{"label":"Accrued Liabilities, Current","description":"Carrying value as of the balance sheet date of obligations incurred and payable, pertaining to costs that are statutory in nature, are incurred on contractual obligations, or accumulate over time and for which invoices have not yet been received or will not be rendered. Examples include taxes, interest, rent and utilities. Used to reflect the current portion of the liabilities (due within one year or within the normal operating cycle if longer).","units":{"USD":[{"end":"2020-12-31","val":0,"accn":"0001193125-21-173844","fy":2021,"fp":"Q1","form":"10-Q/A","filed":"2021-05-27"},{"end":"2020-12-31","val":0,"accn":"0001193125-21-247908","fy":2021,"fp":"Q2","form":"10-Q","filed":"2021-08-16"},{"end":"2020-12-31","val":0,"accn":"0001193125-21-334994","fy":2021,"fp":"Q3","form":"10-Q","filed":"2021-11-19","frame":"CY2020Q4I"},{"end":"2021-03-31","val":140787,"accn":"0001193125-21-173844","fy":2021,"fp":"Q1","form":"10-Q/A","filed":"2021-05-27","frame":"CY2021Q1I"},{"end":"2021-06-30","val":221514,"accn":"0001193125-21-247908","fy":2021,"fp":"Q2","form":"10-Q","filed":"2021-08-16","frame":"CY2021Q2I"},{"end":"2021-09-30","val":251032,"accn":"0001193125-21-334994","fy":2021,"fp":"Q3","form":"10-Q","filed":"2021-11-19","frame":"CY2021Q3I"}]}},"AdditionalPaidInCapital":{"label":"Additional Paid in Capital","description":"Excess of issue price over par or stated value of the entity's capital stock and amounts received from other transactions involving the entity's stock or stockholders. Includes adjustments to additional paid in capital. Some examples of such adjustments include recording the issuance of debt with a beneficial conversion feature and certain tax consequences of equity instruments awarded to employees. Use this element for the aggregate amount of additional paid-in capital associated with common and preferred stock. For additional paid-in capital associated with only common stock, use the element additional paid in capital, common stock. For additional paid-in capital associated with only preferred stock, use the element additional paid in capital, preferred stock.","units":{"USD":[{"end":"2020-12-31","val":24425,"accn":"0001193125-21-173844","fy":2021,"fp":"Q1","form":"10-Q/A","filed":"2021-05-27"},{"end":"2020-12-31","val":24425,"accn":"0001193125-21-247908","fy":2021,"fp":"Q2","form":"10-Q","filed":"2021-08-16"},{"end":"2020-12-31","val":24425,"accn":"0001193125-21-334994","fy":2021,"fp":"Q3","form":"10-Q","filed":"2021-11-19","frame":"CY2020Q4I"},{"end":"2021-03-19","val":5519053,"accn":"0001193125-21-173844","fy":2021,"fp":"Q1","form":"10-Q/A","filed":"2021-05-27"},{"end":"2021-03-31","val":5425632,"accn":"0001193125-21-173844","fy":2021,"fp":"Q1","form":"10-Q/A","filed":"2021-05-27","frame":"CY2021Q1I"},{"end":"2021-06-30","val":3560195,"accn":"0001193125-21-247908","fy":2021,"fp":"Q2","form":"10-Q","filed":"2021-08-16","frame":"CY2021Q2I"},{"end":"2021-09-30","val":0,"accn":"0001193125-21-334994","fy":2021,"fp":"Q3","form":"10-Q","filed":"2021-11-19","frame":"CY2021Q3I"}]}},"AdjustmentsToAdditionalPaidInCapitalStockIssuedIssuanceCosts":{"label":"Adjustments to Additional Paid in Capital, Stock Issued, Issuance Costs","description":"Amount of decrease in additional paid in capital (APIC) resulting from direct costs associated with issuing stock. Includes, but is not limited to, legal and accounting fees and direct costs associated with stock issues under a shelf registration.","units":{"USD":[{"start":"2021-01-01","end":"2021-03-31","val":9485820,"accn":"0001193125-21-173844","fy":2021,"fp":"Q1","form":"10-Q/A","filed":"2021-05-27","frame":"CY2021Q1"},{"start":"2021-01-01","end":"2021-06-30","val":9485819,"accn":"0001193125-21-247908","fy":2021,"fp":"Q2","form":"10-Q","filed":"2021-08-16"},{"start":"2021-01-01","end":"2021-09-30","val":9485819,"accn":"0001193125-21-334994","fy":2021,"fp":"Q3","form":"10-Q","filed":"2021-11-19"}]}},"AdjustmentsToAdditionalPaidInCapitalWarrantIssued":{"label":"Adjustments to Additional Paid in Capital, Warrant Issued","description":"Amount of increase in additional paid in capital (APIC) resulting from the issuance of warrants. Includes allocation of proceeds of debt securities issued with detachable stock purchase warrants.","units":{"USD":[{"start":"2021-01-01","end":"2021-03-31","val":4875000,"accn":"0001193125-21-173844","fy":2021,"fp":"Q1","form":"10-Q/A","filed":"2021-05-27","frame":"CY2021Q1"},{"start":"2021-01-01","end":"2021-06-30","val":4875000,"accn":"0001193125-21-247908","fy":2021,"fp":"Q2","form":"10-Q","filed":"2021-08-16"}]}},"AntidilutiveSecuritiesExcludedFromComputationOfEarningsPerShareAmount":{"label":"Antidilutive Securities Excluded from Computation of Earnings Per Share, Amount","description":"Securities (including those issuable pursuant to contingent stock agreements) that could potentially dilute basic earnings per share (EPS) or earnings per unit (EPU) in the future that were not included in the computation of diluted EPS or EPU because to do so would increase EPS or EPU amounts or decrease loss per share or unit amounts for the period presented.","units":{"shares":[{"start":"2021-01-01","end":"2021-03-31","val":13625000,"accn":"0001193125-21-173844","fy":2021,"fp":"Q1","form":"10-Q/A","filed":"2021-05-27","frame":"CY2021Q1"},{"start":"2021-01-01","end":"2021-06-30","val":13625000,"accn":"0001193125-21-247908","fy":2021,"fp":"Q2","form":"10-Q","filed":"2021-08-16"},{"start":"2021-01-01","end":"2021-09-30","val":13625000,"accn":"0001193125-21-334994","fy":2021,"fp":"Q3","form":"10-Q","filed":"2021-11-19"}]}},"Assets":{"label":"Assets","description":"Sum of the carrying amounts as of the balance sheet date of all assets that are recognized. Assets are probable future economic benefits obtained or controlled by an entity as a result of past transactions or events.","units":{"USD":[{"end":"2020-12-31","val":25000,"accn":"0001193125-21-173844","fy":2021,"fp":"Q1","form":"10-Q/A","filed":"2021-05-27"},{"end":"2020-12-31","val":25000,"accn":"0001193125-21-247908","fy":2021,"fp":"Q2","form":"10-Q","filed":"2021-08-16"},{"end":"2020-12-31","val":25000,"accn":"0001193125-21-334994","fy":2021,"fp":"Q3","form":"10-Q","filed":"2021-11-19","frame":"CY2020Q4I"},{"end":"2021-03-19","val":177674936,"accn":"0001193125-21-173844","fy":2021,"fp":"Q1","form":"10-Q/A","filed":"2021-05-27"},{"end":"2021-03-31","val":176938972,"accn":"0001193125-21-173844","fy":2021,"fp":"Q1","form":"10-Q/A","filed":"2021-05-27","frame":"CY2021Q1I"},{"end":"2021-06-30","val":176505909,"accn":"0001193125-21-247908","fy":2021,"fp":"Q2","form":"10-Q","filed":"2021-08-16","frame":"CY2021Q2I"},{"end":"2021-09-30","val":176226258,"accn":"0001193125-21-334994","fy":2021,"fp":"Q3","form":"10-Q","filed":"2021-11-19","frame":"CY2021Q3I"}]}},"AssetsCurrent":{"label":"Assets, Current","description":"Sum of the carrying amounts as of the balance sheet date of all assets that are expected to be realized in cash, sold, or consumed within one year (or the normal operating cycle, if longer). Assets are probable future economic benefits obtained or controlled by an entity as a result of past transactions or events.","units":{"USD":[{"end":"2020-12-31","val":25000,"accn":"0001193125-21-173844","fy":2021,"fp":"Q1","form":"10-Q/A","filed":"2021-05-27"},{"end":"2020-12-31","val":25000,"accn":"0001193125-21-247908","fy":2021,"fp":"Q2","form":"10-Q","filed":"2021-08-16"},{"end":"2020-12-31","val":25000,"accn":"0001193125-21-334994","fy":2021,"fp":"Q3","form":"10-Q","filed":"2021-11-19","frame":"CY2020Q4I"},{"end":"2021-03-31","val":1937889,"accn":"0001193125-21-173844","fy":2021,"fp":"Q1","form":"10-Q/A","filed":"2021-05-27","frame":"CY2021Q1I"},{"end":"2021-06-30","val":1030848,"accn":"0001193125-21-247908","fy":2021,"fp":"Q2","form":"10-Q","filed":"2021-08-16","frame":"CY2021Q2I"},{"end":"2021-09-30","val":921135,"accn":"0001193125-21-334994","fy":2021,"fp":"Q3","form":"10-Q","filed":"2021-11-19","frame":"CY2021Q3I"}]}},"AssetsHeldInTrustNoncurrent":{"label":"Assets Held-in-trust, Noncurrent","description":"The amount of cash, securities, or other assets held by a third-party trustee pursuant to the terms of an agreement which assets are available to be used by beneficiaries to that agreement only within the specific terms thereof and which agreement is expected to terminate more than one year from the balance sheet date (or operating cycle, if longer) at which time the assets held-in-trust will be released or forfeited.","units":{"USD":[{"end":"2021-03-31","val":175001083,"accn":"0001193125-21-173844","fy":2021,"fp":"Q1","form":"10-Q/A","filed":"2021-05-27","frame":"CY2021Q1I"},{"end":"2021-06-30","val":175007386,"accn":"0001193125-21-247908","fy":2021,"fp":"Q2","form":"10-Q","filed":"2021-08-16","frame":"CY2021Q2I"},{"end":"2021-09-30","val":175009638,"accn":"0001193125-21-334994","fy":2021,"fp":"Q3","form":"10-Q","filed":"2021-11-19","frame":"CY2021Q3I"}]}},"CashAndCashEquivalentsAtCarryingValue":{"label":"Cash and Cash Equivalents, at Carrying Value","description":"Amount of currency on hand as well as demand deposits with banks or financial institutions. Includes other kinds of accounts that have the general characteristics of demand deposits. Also includes short-term, highly liquid investments that are both readily convertible to known amounts of cash and so near their maturity that they present insignificant risk of changes in value because of changes in interest rates. Excludes cash and cash equivalents within disposal group and discontinued operation.","units":{"USD":[{"end":"2020-12-31","val":0,"accn":"0001193125-21-173844","fy":2021,"fp":"Q1","form":"10-Q/A","filed":"2021-05-27"},{"end":"2020-12-31","val":0,"accn":"0001193125-21-247908","fy":2021,"fp":"Q2","form":"10-Q","filed":"2021-08-16"},{"end":"2020-12-31","val":0,"accn":"0001193125-21-334994","fy":2021,"fp":"Q3","form":"10-Q","filed":"2021-11-19","frame":"CY2020Q4I"},{"end":"2021-03-31","val":457434,"accn":"0001193125-21-173844","fy":2021,"fp":"Q1","form":"10-Q/A","filed":"2021-05-27","frame":"CY2021Q1I"},{"end":"2021-06-30","val":209156,"accn":"0001193125-21-247908","fy":2021,"fp":"Q2","form":"10-Q","filed":"2021-08-16","frame":"CY2021Q2I"},{"end":"2021-09-30","val":150065,"accn":"0001193125-21-334994","fy":2021,"fp":"Q3","form":"10-Q","filed":"2021-11-19","frame":"CY2021Q3I"}]}},"CashAndCashEquivalentsPeriodIncreaseDecrease":{"label":"Cash and Cash Equivalents, Period Increase (Decrease)","description":"Amount of increase (decrease) in cash and cash equivalents. Cash and cash equivalents are the amount of currency on hand as well as demand deposits with banks or financial institutions. Includes other kinds of accounts that have the general characteristics of demand deposits. Also includes short-term, highly liquid investments that are both readily convertible to known amounts of cash and so near their maturity that they present insignificant risk of changes in value because of changes in interest rates. Includes effect from exchange rate changes.","units":{"USD":[{"start":"2021-01-01","end":"2021-03-31","val":457434,"accn":"0001193125-21-173844","fy":2021,"fp":"Q1","form":"10-Q/A","filed":"2021-05-27","frame":"CY2021Q1"},{"start":"2021-01-01","end":"2021-06-30","val":209156,"accn":"0001193125-21-247908","fy":2021,"fp":"Q2","form":"10-Q","filed":"2021-08-16"},{"start":"2021-01-01","end":"2021-09-30","val":150065,"accn":"0001193125-21-334994","fy":2021,"fp":"Q3","form":"10-Q","filed":"2021-11-19"}]}},"CashFDICInsuredAmount":{"label":"Cash, FDIC Insured Amount","description":"The amount of cash deposited in financial institutions as of the balance sheet date that is insured by the Federal Deposit Insurance Corporation.","units":{"USD":[{"end":"2021-03-31","val":250000,"accn":"0001193125-21-173844","fy":2021,"fp":"Q1","form":"10-Q/A","filed":"2021-05-27","frame":"CY2021Q1I"},{"end":"2021-06-30","val":250000,"accn":"0001193125-21-247908","fy":2021,"fp":"Q2","form":"10-Q","filed":"2021-08-16","frame":"CY2021Q2I"},{"end":"2021-09-30","val":250000,"accn":"0001193125-21-334994","fy":2021,"fp":"Q3","form":"10-Q","filed":"2021-11-19","frame":"CY2021Q3I"}]}},"DerivativeLiabilitiesNoncurrent":{"label":"Derivative Liability, Noncurrent","description":"Fair value, after the effects of master netting arrangements, of a financial liability or contract with one or more underlyings, notional amount or payment provision or both, and the contract can be net settled by means outside the contract or delivery of an asset, expected to be settled after one year or the normal operating cycle, if longer. Includes assets not subject to a master netting arrangement and not elected to be offset.","units":{"USD":[{"end":"2020-12-31","val":0,"accn":"0001193125-21-173844","fy":2021,"fp":"Q1","form":"10-Q/A","filed":"2021-05-27"},{"end":"2020-12-31","val":0,"accn":"0001193125-21-247908","fy":2021,"fp":"Q2","form":"10-Q","filed":"2021-08-16"},{"end":"2020-12-31","val":0,"accn":"0001193125-21-334994","fy":2021,"fp":"Q3","form":"10-Q","filed":"2021-11-19","frame":"CY2020Q4I"},{"end":"2021-03-19","val":13275000,"accn":"0001193125-21-173844","fy":2021,"fp":"Q1","form":"10-Q/A","filed":"2021-05-27"},{"end":"2021-03-31","val":12963750,"accn":"0001193125-21-173844","fy":2021,"fp":"Q1","form":"10-Q/A","filed":"2021-05-27","frame":"CY2021Q1I"},{"end":"2021-06-30","val":10598750,"accn":"0001193125-21-247908","fy":2021,"fp":"Q2","form":"10-Q","filed":"2021-08-16","frame":"CY2021Q2I"},{"end":"2021-09-30","val":6958750,"accn":"0001193125-21-334994","fy":2021,"fp":"Q3","form":"10-Q","filed":"2021-11-19","frame":"CY2021Q3I"}]}},"DueFromRelatedPartiesCurrent":{"label":"Due from Related Parties, Current","description":"The aggregate amount of receivables to be collected from related parties where one party can exercise control or significant influence over another party; including affiliates, owners or officers and their immediate families, pension trusts, and so forth, at the financial statement date. which are usually due within one year (or one business cycle).","units":{"USD":[{"end":"2020-12-31","val":25000,"accn":"0001193125-21-173844","fy":2021,"fp":"Q1","form":"10-Q/A","filed":"2021-05-27"},{"end":"2020-12-31","val":25000,"accn":"0001193125-21-247908","fy":2021,"fp":"Q2","form":"10-Q","filed":"2021-08-16"},{"end":"2020-12-31","val":25000,"accn":"0001193125-21-334994","fy":2021,"fp":"Q3","form":"10-Q","filed":"2021-11-19","frame":"CY2020Q4I"},{"end":"2021-03-31","val":0,"accn":"0001193125-21-173844","fy":2021,"fp":"Q1","form":"10-Q/A","filed":"2021-05-27","frame":"CY2021Q1I"},{"end":"2021-06-30","val":0,"accn":"0001193125-21-247908","fy":2021,"fp":"Q2","form":"10-Q","filed":"2021-08-16","frame":"CY2021Q2I"},{"end":"2021-09-30","val":0,"accn":"0001193125-21-334994","fy":2021,"fp":"Q3","form":"10-Q","filed":"2021-11-19","frame":"CY2021Q3I"}]}},"DueToRelatedPartiesCurrent":{"label":"Due to Related Parties, Current","description":"Carrying amount as of the balance sheet date of obligations due all related parties. For classified balance sheets, represents the current portion of such liabilities (due within one year or within the normal operating cycle if longer).","units":{"USD":[{"end":"2021-03-19","val":535000,"accn":"0001193125-21-173844","fy":2021,"fp":"Q1","form":"10-Q/A","filed":"2021-05-27","frame":"CY2021Q1I"}]}},"FairValueAdjustmentOfWarrants":{"label":"Fair Value Adjustment of Warrants","description":"Amount of expense (income) related to adjustment to fair value of warrant liability.","units":{"USD":[{"start":"2021-01-01","end":"2021-03-31","val":-311250,"accn":"0001193125-21-173844","fy":2021,"fp":"Q1","form":"10-Q/A","filed":"2021-05-27","frame":"CY2021Q1"},{"start":"2021-01-01","end":"2021-06-30","val":-2676250,"accn":"0001193125-21-247908","fy":2021,"fp":"Q2","form":"10-Q","filed":"2021-08-16"},{"start":"2021-04-01","end":"2021-06-30","val":-2365000,"accn":"0001193125-21-247908","fy":2021,"fp":"Q2","form":"10-Q","filed":"2021-08-16","frame":"CY2021Q2"},{"start":"2021-01-01","end":"2021-09-30","val":-6316250,"accn":"0001193125-21-334994","fy":2021,"fp":"Q3","form":"10-Q","filed":"2021-11-19"},{"start":"2021-07-01","end":"2021-09-30","val":-3640000,"accn":"0001193125-21-334994","fy":2021,"fp":"Q3","form":"10-Q","filed":"2021-11-19","frame":"CY2021Q3"}]}},"GeneralAndAdministrativeExpense":{"label":"General and Administrative Expense","description":"The aggregate total of expenses of managing and administering the affairs of an entity, including affiliates of the reporting entity, which are not directly or indirectly associated with the manufacture, sale or creation of a product or product line.","units":{"USD":[{"start":"2021-01-01","end":"2021-03-31","val":250997,"accn":"0001193125-21-173844","fy":2021,"fp":"Q1","form":"10-Q/A","filed":"2021-05-27","frame":"CY2021Q1"},{"start":"2021-01-01","end":"2021-06-30","val":656786,"accn":"0001193125-21-247908","fy":2021,"fp":"Q2","form":"10-Q","filed":"2021-08-16"},{"start":"2021-04-01","end":"2021-06-30","val":405789,"accn":"0001193125-21-247908","fy":2021,"fp":"Q2","form":"10-Q","filed":"2021-08-16","frame":"CY2021Q2"},{"start":"2021-01-01","end":"2021-09-30","val":1007019,"accn":"0001193125-21-334994","fy":2021,"fp":"Q3","form":"10-Q","filed":"2021-11-19"},{"start":"2021-07-01","end":"2021-09-30","val":350233,"accn":"0001193125-21-334994","fy":2021,"fp":"Q3","form":"10-Q","filed":"2021-11-19","frame":"CY2021Q3"}]}},"IncomeTaxExpenseBenefit":{"label":"Income Tax Expense (Benefit)","description":"Amount of current income tax expense (benefit) and deferred income tax expense (benefit) pertaining to continuing operations.","units":{"USD":[{"start":"2021-01-01","end":"2021-03-31","val":0,"accn":"0001193125-21-173844","fy":2021,"fp":"Q1","form":"10-Q/A","filed":"2021-05-27","frame":"CY2021Q1"}]}},"IncreaseDecreaseInAccountsPayableAndAccruedLiabilities":{"label":"Increase (Decrease) in Accounts Payable and Accrued Liabilities","description":"The increase (decrease) during the reporting period in the amounts payable to vendors for goods and services received and the amount of obligations and expenses incurred but not paid.","units":{"USD":[{"start":"2021-01-01","end":"2021-03-31","val":238584,"accn":"0001193125-21-173844","fy":2021,"fp":"Q1","form":"10-Q/A","filed":"2021-05-27","frame":"CY2021Q1"},{"start":"2021-01-01","end":"2021-06-30","val":228823,"accn":"0001193125-21-247908","fy":2021,"fp":"Q2","form":"10-Q","filed":"2021-08-16"},{"start":"2021-01-01","end":"2021-09-30","val":297150,"accn":"0001193125-21-334994","fy":2021,"fp":"Q3","form":"10-Q","filed":"2021-11-19"}]}},"IncreaseDecreaseInAccruedTaxesPayable":{"label":"Increase (Decrease) in Accrued Taxes Payable","description":"The increase (decrease) during the reporting period of all taxes owed but not paid, including income, property and other taxes.","units":{"USD":[{"start":"2021-01-01","end":"2021-06-30","val":100000,"accn":"0001193125-21-247908","fy":2021,"fp":"Q2","form":"10-Q","filed":"2021-08-16"},{"start":"2021-01-01","end":"2021-09-30","val":150000,"accn":"0001193125-21-334994","fy":2021,"fp":"Q3","form":"10-Q","filed":"2021-11-19"}]}},"IncreaseDecreaseInPrepaidDeferredExpenseAndOtherAssets":{"label":"Increase (Decrease) in Prepaid Expense and Other Assets","description":"Amount of increase (decrease) in prepaid expenses, and assets classified as other.","units":{"USD":[{"start":"2021-01-01","end":"2021-06-30","val":1289367,"accn":"0001193125-21-247908","fy":2021,"fp":"Q2","form":"10-Q","filed":"2021-08-16"},{"start":"2021-01-01","end":"2021-09-30","val":1066555,"accn":"0001193125-21-334994","fy":2021,"fp":"Q3","form":"10-Q","filed":"2021-11-19"}]}},"IncreaseDecreaseInPrepaidExpense":{"label":"Increase (Decrease) in Prepaid Expense","description":"The increase (decrease) during the reporting period in the amount of outstanding money paid in advance for goods or services that bring economic benefits for future periods.","units":{"USD":[{"start":"2021-01-01","end":"2021-03-31","val":1480455,"accn":"0001193125-21-173844","fy":2021,"fp":"Q1","form":"10-Q/A","filed":"2021-05-27","frame":"CY2021Q1"}]}},"InvestmentIncomeInterest":{"label":"Investment Income, Interest","description":"Amount before accretion (amortization) of purchase discount (premium) of interest income on nonoperating securities.","units":{"USD":[{"start":"2021-01-01","end":"2021-03-31","val":1102,"accn":"0001193125-21-173844","fy":2021,"fp":"Q1","form":"10-Q/A","filed":"2021-05-27","frame":"CY2021Q1"},{"start":"2021-01-01","end":"2021-06-30","val":7413,"accn":"0001193125-21-247908","fy":2021,"fp":"Q2","form":"10-Q","filed":"2021-08-16"},{"start":"2021-04-01","end":"2021-06-30","val":6311,"accn":"0001193125-21-247908","fy":2021,"fp":"Q2","form":"10-Q","filed":"2021-08-16","frame":"CY2021Q2"},{"start":"2021-01-01","end":"2021-09-30","val":9669,"accn":"0001193125-21-334994","fy":2021,"fp":"Q3","form":"10-Q","filed":"2021-11-19"},{"start":"2021-07-01","end":"2021-09-30","val":2256,"accn":"0001193125-21-334994","fy":2021,"fp":"Q3","form":"10-Q","filed":"2021-11-19","frame":"CY2021Q3"}]}},"Liabilities":{"label":"Liabilities","description":"Sum of the carrying amounts as of the balance sheet date of all liabilities that are recognized. Liabilities are probable future sacrifices of economic benefits arising from present obligations of an entity to transfer assets or provide services to other entities in the future.","units":{"USD":[{"end":"2020-12-31","val":0,"accn":"0001193125-21-173844","fy":2021,"fp":"Q1","form":"10-Q/A","filed":"2021-05-27"},{"end":"2020-12-31","val":0,"accn":"0001193125-21-247908","fy":2021,"fp":"Q2","form":"10-Q","filed":"2021-08-16"},{"end":"2020-12-31","val":0,"accn":"0001193125-21-334994","fy":2021,"fp":"Q3","form":"10-Q","filed":"2021-11-19","frame":"CY2020Q4I"},{"end":"2021-03-19","val":21024910,"accn":"0001193125-21-173844","fy":2021,"fp":"Q1","form":"10-Q/A","filed":"2021-05-27"},{"end":"2021-03-31","val":20226159,"accn":"0001193125-21-173844","fy":2021,"fp":"Q1","form":"10-Q/A","filed":"2021-05-27","frame":"CY2021Q1I"},{"end":"2021-06-30","val":17927573,"accn":"0001193125-21-247908","fy":2021,"fp":"Q2","form":"10-Q","filed":"2021-08-16","frame":"CY2021Q2I"},{"end":"2021-09-30","val":14405900,"accn":"0001193125-21-334994","fy":2021,"fp":"Q3","form":"10-Q","filed":"2021-11-19","frame":"CY2021Q3I"}]}},"LiabilitiesAndStockholdersEquity":{"label":"Liabilities and Equity","description":"Amount of liabilities and equity items, including the portion of equity attributable to noncontrolling interests, if any.","units":{"USD":[{"end":"2020-12-31","val":25000,"accn":"0001193125-21-173844","fy":2021,"fp":"Q1","form":"10-Q/A","filed":"2021-05-27"},{"end":"2020-12-31","val":25000,"accn":"0001193125-21-247908","fy":2021,"fp":"Q2","form":"10-Q","filed":"2021-08-16"},{"end":"2020-12-31","val":25000,"accn":"0001193125-21-334994","fy":2021,"fp":"Q3","form":"10-Q","filed":"2021-11-19","frame":"CY2020Q4I"},{"end":"2021-03-19","val":177674936,"accn":"0001193125-21-173844","fy":2021,"fp":"Q1","form":"10-Q/A","filed":"2021-05-27"},{"end":"2021-03-31","val":176938972,"accn":"0001193125-21-173844","fy":2021,"fp":"Q1","form":"10-Q/A","filed":"2021-05-27","frame":"CY2021Q1I"},{"end":"2021-06-30","val":176505909,"accn":"0001193125-21-247908","fy":2021,"fp":"Q2","form":"10-Q","filed":"2021-08-16","frame":"CY2021Q2I"},{"end":"2021-09-30","val":176226258,"accn":"0001193125-21-334994","fy":2021,"fp":"Q3","form":"10-Q","filed":"2021-11-19","frame":"CY2021Q3I"}]}},"LiabilitiesCurrent":{"label":"Liabilities, Current","description":"Total obligations incurred as part of normal operations that are expected to be paid during the following twelve months or within one business cycle, if longer.","units":{"USD":[{"end":"2020-12-31","val":0,"accn":"0001193125-21-173844","fy":2021,"fp":"Q1","form":"10-Q/A","filed":"2021-05-27"},{"end":"2020-12-31","val":0,"accn":"0001193125-21-247908","fy":2021,"fp":"Q2","form":"10-Q","filed":"2021-08-16"},{"end":"2020-12-31","val":0,"accn":"0001193125-21-334994","fy":2021,"fp":"Q3","form":"10-Q","filed":"2021-11-19","frame":"CY2020Q4I"},{"end":"2021-03-19","val":749910,"accn":"0001193125-21-173844","fy":2021,"fp":"Q1","form":"10-Q/A","filed":"2021-05-27"},{"end":"2021-03-31","val":262409,"accn":"0001193125-21-173844","fy":2021,"fp":"Q1","form":"10-Q/A","filed":"2021-05-27","frame":"CY2021Q1I"},{"end":"2021-06-30","val":328823,"accn":"0001193125-21-247908","fy":2021,"fp":"Q2","form":"10-Q","filed":"2021-08-16","frame":"CY2021Q2I"},{"end":"2021-09-30","val":447150,"accn":"0001193125-21-334994","fy":2021,"fp":"Q3","form":"10-Q","filed":"2021-11-19","frame":"CY2021Q3I"}]}},"NetCashProvidedByUsedInFinancingActivities":{"label":"Net Cash Provided by (Used in) Financing Activities","description":"Amount of cash inflow (outflow) from financing activities, including discontinued operations. Financing activity cash flows include obtaining resources from owners and providing them with a return on, and a return of, their investment; borrowing money and repaying amounts borrowed, or settling the obligation; and obtaining and paying for other resources obtained from creditors on long-term credit.","units":{"USD":[{"start":"2021-01-01","end":"2021-03-31","val":176950283,"accn":"0001193125-21-173844","fy":2021,"fp":"Q1","form":"10-Q/A","filed":"2021-05-27","frame":"CY2021Q1"},{"start":"2021-01-01","end":"2021-06-30","val":176926458,"accn":"0001193125-21-247908","fy":2021,"fp":"Q2","form":"10-Q","filed":"2021-08-16"},{"start":"2021-01-01","end":"2021-09-30","val":176926458,"accn":"0001193125-21-334994","fy":2021,"fp":"Q3","form":"10-Q","filed":"2021-11-19"}]}},"NetCashProvidedByUsedInInvestingActivities":{"label":"Net Cash Provided by (Used in) Investing Activities","description":"Amount of cash inflow (outflow) from investing activities, including discontinued operations. Investing activity cash flows include making and collecting loans and acquiring and disposing of debt or equity instruments and property, plant, and equipment and other productive assets.","units":{"USD":[{"start":"2021-01-01","end":"2021-03-31","val":-175000000,"accn":"0001193125-21-173844","fy":2021,"fp":"Q1","form":"10-Q/A","filed":"2021-05-27","frame":"CY2021Q1"},{"start":"2021-01-01","end":"2021-06-30","val":-175000000,"accn":"0001193125-21-247908","fy":2021,"fp":"Q2","form":"10-Q","filed":"2021-08-16"},{"start":"2021-01-01","end":"2021-09-30","val":-175000000,"accn":"0001193125-21-334994","fy":2021,"fp":"Q3","form":"10-Q","filed":"2021-11-19"}]}},"NetCashProvidedByUsedInOperatingActivities":{"label":"Net Cash Provided by (Used in) Operating Activities","description":"Amount of cash inflow (outflow) from operating activities, including discontinued operations. Operating activity cash flows include transactions, adjustments, and changes in value not defined as investing or financing activities.","units":{"USD":[{"start":"2021-01-01","end":"2021-03-31","val":-1492849,"accn":"0001193125-21-173844","fy":2021,"fp":"Q1","form":"10-Q/A","filed":"2021-05-27","frame":"CY2021Q1"},{"start":"2021-01-01","end":"2021-06-30","val":-1717302,"accn":"0001193125-21-247908","fy":2021,"fp":"Q2","form":"10-Q","filed":"2021-08-16"},{"start":"2021-01-01","end":"2021-09-30","val":-1776393,"accn":"0001193125-21-334994","fy":2021,"fp":"Q3","form":"10-Q","filed":"2021-11-19"}]}},"NetIncomeLoss":{"label":"Net Income (Loss) Attributable to Parent","description":"The portion of profit or loss for the period, net of income taxes, which is attributable to the parent.","units":{"USD":[{"start":"2021-01-01","end":"2021-03-31","val":-426367,"accn":"0001193125-21-173844","fy":2021,"fp":"Q1","form":"10-Q/A","filed":"2021-05-27"},{"start":"2021-01-01","end":"2021-03-31","val":-426367,"accn":"0001193125-21-334994","fy":2021,"fp":"Q3","form":"10-Q","filed":"2021-11-19","frame":"CY2021Q1"},{"start":"2021-01-01","end":"2021-06-30","val":1439155,"accn":"0001193125-21-247908","fy":2021,"fp":"Q2","form":"10-Q","filed":"2021-08-16"},{"start":"2021-04-01","end":"2021-06-30","val":1865522,"accn":"0001193125-21-247908","fy":2021,"fp":"Q2","form":"10-Q","filed":"2021-08-16"},{"start":"2021-04-01","end":"2021-06-30","val":1865522,"accn":"0001193125-21-334994","fy":2021,"fp":"Q3","form":"10-Q","filed":"2021-11-19","frame":"CY2021Q2"},{"start":"2021-01-01","end":"2021-09-30","val":4681177,"accn":"0001193125-21-334994","fy":2021,"fp":"Q3","form":"10-Q","filed":"2021-11-19"},{"start":"2021-07-01","end":"2021-09-30","val":3242023,"accn":"0001193125-21-334994","fy":2021,"fp":"Q3","form":"10-Q","filed":"2021-11-19","frame":"CY2021Q3"}]}},"NonoperatingIncomeExpense":{"label":"Nonoperating Income (Expense)","description":"The aggregate amount of income or expense from ancillary business-related activities (that is to say, excluding major activities considered part of the normal operations of the business).","units":{"USD":[{"start":"2021-01-01","end":"2021-03-31","val":-175370,"accn":"0001193125-21-173844","fy":2021,"fp":"Q1","form":"10-Q/A","filed":"2021-05-27","frame":"CY2021Q1"},{"start":"2021-01-01","end":"2021-06-30","val":2195941,"accn":"0001193125-21-247908","fy":2021,"fp":"Q2","form":"10-Q","filed":"2021-08-16"},{"start":"2021-04-01","end":"2021-06-30","val":2371311,"accn":"0001193125-21-247908","fy":2021,"fp":"Q2","form":"10-Q","filed":"2021-08-16","frame":"CY2021Q2"},{"start":"2021-01-01","end":"2021-09-30","val":5838196,"accn":"0001193125-21-334994","fy":2021,"fp":"Q3","form":"10-Q","filed":"2021-11-19"},{"start":"2021-07-01","end":"2021-09-30","val":3642256,"accn":"0001193125-21-334994","fy":2021,"fp":"Q3","form":"10-Q","filed":"2021-11-19","frame":"CY2021Q3"}]}},"OperatingIncomeLoss":{"label":"Operating Income (Loss)","description":"The net result for the period of deducting operating expenses from operating revenues.","units":{"USD":[{"start":"2021-01-01","end":"2021-03-31","val":-250997,"accn":"0001193125-21-173844","fy":2021,"fp":"Q1","form":"10-Q/A","filed":"2021-05-27","frame":"CY2021Q1"},{"start":"2021-01-01","end":"2021-06-30","val":-756786,"accn":"0001193125-21-247908","fy":2021,"fp":"Q2","form":"10-Q","filed":"2021-08-16"},{"start":"2021-04-01","end":"2021-06-30","val":-505789,"accn":"0001193125-21-247908","fy":2021,"fp":"Q2","form":"10-Q","filed":"2021-08-16","frame":"CY2021Q2"},{"start":"2021-01-01","end":"2021-09-30","val":-1157019,"accn":"0001193125-21-334994","fy":2021,"fp":"Q3","form":"10-Q","filed":"2021-11-19"},{"start":"2021-07-01","end":"2021-09-30","val":-400233,"accn":"0001193125-21-334994","fy":2021,"fp":"Q3","form":"10-Q","filed":"2021-11-19","frame":"CY2021Q3"}]}},"PaymentOfFinancingAndStockIssuanceCosts":{"label":"Payment of Financing and Stock Issuance Costs","description":"The total of the cash outflow during the period which has been paid to third parties in connection with debt origination, which will be amortized over the remaining maturity period of the associated long-term debt and the cost incurred directly for the issuance of equity securities.","units":{"USD":[{"start":"2021-01-01","end":"2021-03-31","val":2949717,"accn":"0001193125-21-173844","fy":2021,"fp":"Q1","form":"10-Q/A","filed":"2021-05-27","frame":"CY2021Q1"},{"start":"2021-01-01","end":"2021-06-30","val":2973542,"accn":"0001193125-21-247908","fy":2021,"fp":"Q2","form":"10-Q","filed":"2021-08-16"},{"start":"2021-01-01","end":"2021-09-30","val":2973542,"accn":"0001193125-21-334994","fy":2021,"fp":"Q3","form":"10-Q","filed":"2021-11-19"}]}},"PaymentsForUnderwritingExpense":{"label":"Payments for Underwriting Expense","description":"Cash paid for expenses incurred during underwriting activities (the process to review insurance applications, evaluate risks, accept or reject applications, and determine the premiums to be charged) for insurance companies.","units":{"USD":[{"end":"2021-03-19","val":3500000,"accn":"0001193125-21-247908","fy":2021,"fp":"Q2","form":"10-Q","filed":"2021-08-16"},{"end":"2021-03-19","val":3500000,"accn":"0001193125-21-334994","fy":2021,"fp":"Q3","form":"10-Q","filed":"2021-11-19","frame":"CY2021Q1I"},{"start":"2021-01-01","end":"2021-03-31","val":3500000,"accn":"0001193125-21-173844","fy":2021,"fp":"Q1","form":"10-Q/A","filed":"2021-05-27","frame":"CY2021Q1"}]}},"PaymentsToAcquireTrustPreferredInvestments":{"label":"Payments to Acquire Trust Preferred Investments","description":"The cash outflow for the purchase of trust preferred securities, which possess characteristics of both equity and debt securities.","units":{"USD":[{"start":"2021-01-01","end":"2021-03-31","val":175000000,"accn":"0001193125-21-173844","fy":2021,"fp":"Q1","form":"10-Q/A","filed":"2021-05-27","frame":"CY2021Q1"},{"start":"2021-01-01","end":"2021-06-30","val":175000000,"accn":"0001193125-21-247908","fy":2021,"fp":"Q2","form":"10-Q","filed":"2021-08-16"},{"start":"2021-01-01","end":"2021-09-30","val":175000000,"accn":"0001193125-21-334994","fy":2021,"fp":"Q3","form":"10-Q","filed":"2021-11-19"}]}},"PreferredStockParOrStatedValuePerShare":{"label":"Preferred Stock, Par or Stated Value Per Share","description":"Face amount or stated value per share of preferred stock nonredeemable or redeemable solely at the option of the issuer.","units":{"USD/shares":[{"end":"2020-12-31","val":0.0001,"accn":"0001193125-21-173844","fy":2021,"fp":"Q1","form":"10-Q/A","filed":"2021-05-27"},{"end":"2020-12-31","val":0.0001,"accn":"0001193125-21-247908","fy":2021,"fp":"Q2","form":"10-Q","filed":"2021-08-16","frame":"CY2020Q4I"},{"end":"2021-03-19","val":0.0001,"accn":"0001193125-21-173844","fy":2021,"fp":"Q1","form":"10-Q/A","filed":"2021-05-27"},{"end":"2021-03-31","val":0.0001,"accn":"0001193125-21-173844","fy":2021,"fp":"Q1","form":"10-Q/A","filed":"2021-05-27","frame":"CY2021Q1I"},{"end":"2021-06-30","val":0.0001,"accn":"0001193125-21-247908","fy":2021,"fp":"Q2","form":"10-Q","filed":"2021-08-16","frame":"CY2021Q2I"},{"end":"2021-09-30","val":0.0001,"accn":"0001193125-21-334994","fy":2021,"fp":"Q3","form":"10-Q","filed":"2021-11-19","frame":"CY2021Q3I"}]}},"PreferredStockSharesAuthorized":{"label":"Preferred Stock, Shares Authorized","description":"The maximum number of nonredeemable preferred shares (or preferred stock redeemable solely at the option of the issuer) permitted to be issued by an entity's charter and bylaws.","units":{"shares":[{"end":"2020-12-31","val":1000000,"accn":"0001193125-21-173844","fy":2021,"fp":"Q1","form":"10-Q/A","filed":"2021-05-27"},{"end":"2020-12-31","val":1000000,"accn":"0001193125-21-247908","fy":2021,"fp":"Q2","form":"10-Q","filed":"2021-08-16","frame":"CY2020Q4I"},{"end":"2021-03-31","val":1000000,"accn":"0001193125-21-173844","fy":2021,"fp":"Q1","form":"10-Q/A","filed":"2021-05-27","frame":"CY2021Q1I"},{"end":"2021-06-30","val":1000000,"accn":"0001193125-21-247908","fy":2021,"fp":"Q2","form":"10-Q","filed":"2021-08-16","frame":"CY2021Q2I"},{"end":"2021-09-30","val":1000000,"accn":"0001193125-21-334994","fy":2021,"fp":"Q3","form":"10-Q","filed":"2021-11-19","frame":"CY2021Q3I"}]}},"PreferredStockSharesIssued":{"label":"Preferred Stock, Shares Issued","description":"Total number of nonredeemable preferred shares (or preferred stock redeemable solely at the option of the issuer) issued to shareholders (includes related preferred shares that were issued, repurchased, and remain in the treasury). May be all or portion of the number of preferred shares authorized. Excludes preferred shares that are classified as debt.","units":{"shares":[{"end":"2020-12-31","val":0,"accn":"0001193125-21-173844","fy":2021,"fp":"Q1","form":"10-Q/A","filed":"2021-05-27"},{"end":"2020-12-31","val":0,"accn":"0001193125-21-247908","fy":2021,"fp":"Q2","form":"10-Q","filed":"2021-08-16","frame":"CY2020Q4I"},{"end":"2021-03-31","val":0,"accn":"0001193125-21-173844","fy":2021,"fp":"Q1","form":"10-Q/A","filed":"2021-05-27","frame":"CY2021Q1I"},{"end":"2021-06-30","val":0,"accn":"0001193125-21-247908","fy":2021,"fp":"Q2","form":"10-Q","filed":"2021-08-16","frame":"CY2021Q2I"},{"end":"2021-09-30","val":0,"accn":"0001193125-21-334994","fy":2021,"fp":"Q3","form":"10-Q","filed":"2021-11-19","frame":"CY2021Q3I"}]}},"PreferredStockSharesOutstanding":{"label":"Preferred Stock, Shares Outstanding","description":"Aggregate share number for all nonredeemable preferred stock (or preferred stock redeemable solely at the option of the issuer) held by stockholders. Does not include preferred shares that have been repurchased.","units":{"shares":[{"end":"2020-12-31","val":0,"accn":"0001193125-21-173844","fy":2021,"fp":"Q1","form":"10-Q/A","filed":"2021-05-27"},{"end":"2020-12-31","val":0,"accn":"0001193125-21-247908","fy":2021,"fp":"Q2","form":"10-Q","filed":"2021-08-16","frame":"CY2020Q4I"},{"end":"2021-03-31","val":0,"accn":"0001193125-21-173844","fy":2021,"fp":"Q1","form":"10-Q/A","filed":"2021-05-27","frame":"CY2021Q1I"},{"end":"2021-06-30","val":0,"accn":"0001193125-21-247908","fy":2021,"fp":"Q2","form":"10-Q","filed":"2021-08-16","frame":"CY2021Q2I"},{"end":"2021-09-30","val":0,"accn":"0001193125-21-334994","fy":2021,"fp":"Q3","form":"10-Q","filed":"2021-11-19","frame":"CY2021Q3I"}]}},"PreferredStockValue":{"label":"Preferred Stock, Value, Issued","description":"Aggregate par or stated value of issued nonredeemable preferred stock (or preferred stock redeemable solely at the option of the issuer). This item includes treasury stock repurchased by the entity. Note: elements for number of nonredeemable preferred shares, par value and other disclosure concepts are in another section within stockholders' equity.","units":{"USD":[{"end":"2020-12-31","val":0,"accn":"0001193125-21-173844","fy":2021,"fp":"Q1","form":"10-Q/A","filed":"2021-05-27"},{"end":"2020-12-31","val":0,"accn":"0001193125-21-247908","fy":2021,"fp":"Q2","form":"10-Q","filed":"2021-08-16"},{"end":"2020-12-31","val":0,"accn":"0001193125-21-334994","fy":2021,"fp":"Q3","form":"10-Q","filed":"2021-11-19","frame":"CY2020Q4I"},{"end":"2021-03-19","val":0,"accn":"0001193125-21-173844","fy":2021,"fp":"Q1","form":"10-Q/A","filed":"2021-05-27"},{"end":"2021-03-31","val":0,"accn":"0001193125-21-173844","fy":2021,"fp":"Q1","form":"10-Q/A","filed":"2021-05-27","frame":"CY2021Q1I"},{"end":"2021-06-30","val":0,"accn":"0001193125-21-247908","fy":2021,"fp":"Q2","form":"10-Q","filed":"2021-08-16","frame":"CY2021Q2I"},{"end":"2021-09-30","val":0,"accn":"0001193125-21-334994","fy":2021,"fp":"Q3","form":"10-Q","filed":"2021-11-19","frame":"CY2021Q3I"}]}},"PrepaidExpenseAndOtherAssetsCurrent":{"label":"Prepaid Expense and Other Assets, Current","description":"Amount of asset related to consideration paid in advance for costs that provide economic benefits in future periods, and amount of other assets that are expected to be realized or consumed within one year or the normal operating cycle, if longer.","units":{"USD":[{"end":"2020-12-31","val":0,"accn":"0001193125-21-247908","fy":2021,"fp":"Q2","form":"10-Q","filed":"2021-08-16"},{"end":"2020-12-31","val":0,"accn":"0001193125-21-334994","fy":2021,"fp":"Q3","form":"10-Q","filed":"2021-11-19","frame":"CY2020Q4I"},{"end":"2021-06-30","val":821692,"accn":"0001193125-21-247908","fy":2021,"fp":"Q2","form":"10-Q","filed":"2021-08-16","frame":"CY2021Q2I"},{"end":"2021-09-30","val":771070,"accn":"0001193125-21-334994","fy":2021,"fp":"Q3","form":"10-Q","filed":"2021-11-19","frame":"CY2021Q3I"}]}},"PrepaidExpenseCurrent":{"label":"Prepaid Expense, Current","description":"Amount of asset related to consideration paid in advance for costs that provide economic benefits within a future period of one year or the normal operating cycle, if longer.","units":{"USD":[{"end":"2020-12-31","val":0,"accn":"0001193125-21-173844","fy":2021,"fp":"Q1","form":"10-Q/A","filed":"2021-05-27","frame":"CY2020Q4I"},{"end":"2021-03-31","val":1480455,"accn":"0001193125-21-173844","fy":2021,"fp":"Q1","form":"10-Q/A","filed":"2021-05-27","frame":"CY2021Q1I"}]}},"PrepaidExpenseNoncurrent":{"label":"Prepaid Expense, Noncurrent","description":"Sum of the carrying amounts as of the balance sheet date of amounts paid in advance for expenses which will be charged against earnings in periods after one year or beyond the operating cycle, if longer.","units":{"USD":[{"end":"2021-06-30","val":467675,"accn":"0001193125-21-247908","fy":2021,"fp":"Q2","form":"10-Q","filed":"2021-08-16","frame":"CY2021Q2I"},{"end":"2021-09-30","val":295485,"accn":"0001193125-21-334994","fy":2021,"fp":"Q3","form":"10-Q","filed":"2021-11-19","frame":"CY2021Q3I"}]}},"ProceedsFromIssuanceOfCommonStock":{"label":"Proceeds from Issuance of Common Stock","description":"The cash inflow from the additional capital contribution to the entity.","units":{"USD":[{"start":"2021-01-01","end":"2021-03-31","val":25000,"accn":"0001193125-21-173844","fy":2021,"fp":"Q1","form":"10-Q/A","filed":"2021-05-27","frame":"CY2021Q1"},{"start":"2021-01-01","end":"2021-06-30","val":25000,"accn":"0001193125-21-247908","fy":2021,"fp":"Q2","form":"10-Q","filed":"2021-08-16"},{"start":"2021-01-01","end":"2021-09-30","val":25000,"accn":"0001193125-21-334994","fy":2021,"fp":"Q3","form":"10-Q","filed":"2021-11-19"}]}},"ProceedsFromIssuanceOfWarrants":{"label":"Proceeds from Issuance of Warrants","description":"The cash inflow from issuance of rights to purchase common shares at predetermined price (usually issued together with corporate debt).","units":{"USD":[{"start":"2021-01-01","end":"2021-03-31","val":4875000,"accn":"0001193125-21-173844","fy":2021,"fp":"Q1","form":"10-Q/A","filed":"2021-05-27","frame":"CY2021Q1"},{"start":"2021-01-01","end":"2021-06-30","val":4875000,"accn":"0001193125-21-247908","fy":2021,"fp":"Q2","form":"10-Q","filed":"2021-08-16"},{"start":"2021-01-01","end":"2021-09-30","val":4875000,"accn":"0001193125-21-334994","fy":2021,"fp":"Q3","form":"10-Q","filed":"2021-11-19"}]}},"RetainedEarningsAccumulatedDeficit":{"label":"Retained Earnings (Accumulated Deficit)","description":"The cumulative amount of the reporting entity's undistributed earnings or deficit.","units":{"USD":[{"end":"2020-12-31","val":0,"accn":"0001193125-21-173844","fy":2021,"fp":"Q1","form":"10-Q/A","filed":"2021-05-27"},{"end":"2020-12-31","val":0,"accn":"0001193125-21-247908","fy":2021,"fp":"Q2","form":"10-Q","filed":"2021-08-16"},{"end":"2020-12-31","val":0,"accn":"0001193125-21-334994","fy":2021,"fp":"Q3","form":"10-Q","filed":"2021-11-19","frame":"CY2020Q4I"},{"end":"2021-03-19","val":-519789,"accn":"0001193125-21-173844","fy":2021,"fp":"Q1","form":"10-Q/A","filed":"2021-05-27"},{"end":"2021-03-31","val":-426367,"accn":"0001193125-21-173844","fy":2021,"fp":"Q1","form":"10-Q/A","filed":"2021-05-27","frame":"CY2021Q1I"},{"end":"2021-06-30","val":1439155,"accn":"0001193125-21-247908","fy":2021,"fp":"Q2","form":"10-Q","filed":"2021-08-16","frame":"CY2021Q2I"},{"end":"2021-09-30","val":-13180079,"accn":"0001193125-21-334994","fy":2021,"fp":"Q3","form":"10-Q","filed":"2021-11-19","frame":"CY2021Q3I"}]}},"StockholdersEquity":{"label":"Stockholders' Equity Attributable to Parent","description":"Total of all stockholders' equity (deficit) items, net of receivables from officers, directors, owners, and affiliates of the entity which are attributable to the parent. The amount of the economic entity's stockholders' equity attributable to the parent excludes the amount of stockholders' equity which is allocable to that ownership interest in subsidiary equity which is not attributable to the parent (noncontrolling interest, minority interest). This excludes temporary equity and is sometimes called permanent equity.","units":{"USD":[{"end":"2020-12-31","val":25000,"accn":"0001193125-21-173844","fy":2021,"fp":"Q1","form":"10-Q/A","filed":"2021-05-27"},{"end":"2020-12-31","val":25000,"accn":"0001193125-21-247908","fy":2021,"fp":"Q2","form":"10-Q","filed":"2021-08-16"},{"end":"2020-12-31","val":25000,"accn":"0001193125-21-334994","fy":2021,"fp":"Q3","form":"10-Q","filed":"2021-11-19","frame":"CY2020Q4I"},{"end":"2021-03-19","val":5000001,"accn":"0001193125-21-173844","fy":2021,"fp":"Q1","form":"10-Q/A","filed":"2021-05-27"},{"end":"2021-03-31","val":5000001,"accn":"0001193125-21-173844","fy":2021,"fp":"Q1","form":"10-Q/A","filed":"2021-05-27"},{"end":"2021-03-31","val":5000001,"accn":"0001193125-21-247908","fy":2021,"fp":"Q2","form":"10-Q","filed":"2021-08-16"},{"end":"2021-03-31","val":-18287187,"accn":"0001193125-21-334994","fy":2021,"fp":"Q3","form":"10-Q","filed":"2021-11-19","frame":"CY2021Q1I"},{"end":"2021-06-30","val":5000001,"accn":"0001193125-21-247908","fy":2021,"fp":"Q2","form":"10-Q","filed":"2021-08-16"},{"end":"2021-06-30","val":-16421665,"accn":"0001193125-21-334994","fy":2021,"fp":"Q3","form":"10-Q","filed":"2021-11-19","frame":"CY2021Q2I"},{"end":"2021-09-30","val":-13179642,"accn":"0001193125-21-334994","fy":2021,"fp":"Q3","form":"10-Q","filed":"2021-11-19","frame":"CY2021Q3I"}]}},"StockIssuedDuringPeriodValueNewIssues":{"label":"Stock Issued During Period, Value, New Issues","description":"Equity impact of the value of new stock issued during the period. Includes shares issued in an initial public offering or a secondary public offering.","units":{"USD":[{"start":"2021-01-01","end":"2021-03-31","val":175000000,"accn":"0001193125-21-173844","fy":2021,"fp":"Q1","form":"10-Q/A","filed":"2021-05-27","frame":"CY2021Q1"},{"start":"2021-01-01","end":"2021-06-30","val":175000000,"accn":"0001193125-21-247908","fy":2021,"fp":"Q2","form":"10-Q","filed":"2021-08-16"}]}},"StockIssuedDuringPeriodValueOther":{"label":"Stock Issued During Period, Value, Other","description":"Value of shares of stock issued attributable to transactions classified as other.","units":{"USD":[{"start":"2021-01-01","end":"2021-06-30","val":-1928310,"accn":"0001193125-21-247908","fy":2021,"fp":"Q2","form":"10-Q","filed":"2021-08-16"}]}},"StockIssuedDuringPeriodValueShareBasedCompensationForfeited":{"label":"Shares Issued, Value, Share-based Payment Arrangement, Forfeited","description":"Value of forfeited shares issued under share-based payment arrangement. Excludes employee stock ownership plan (ESOP).","units":{"USD":[{"start":"2021-01-01","end":"2021-03-31","val":0,"accn":"0001193125-21-173844","fy":2021,"fp":"Q1","form":"10-Q/A","filed":"2021-05-27","frame":"CY2021Q1"},{"start":"2021-01-01","end":"2021-06-30","val":0,"accn":"0001193125-21-247908","fy":2021,"fp":"Q2","form":"10-Q","filed":"2021-08-16"},{"start":"2021-04-01","end":"2021-06-30","val":0,"accn":"0001193125-21-247908","fy":2021,"fp":"Q2","form":"10-Q","filed":"2021-08-16"},{"start":"2021-04-01","end":"2021-06-30","val":0,"accn":"0001193125-21-334994","fy":2021,"fp":"Q3","form":"10-Q","filed":"2021-11-19","frame":"CY2021Q2"}]}},"StockOptionPlanExpense":{"label":"Stock or Unit Option Plan Expense","description":"Amount of noncash expense for option under share-based payment arrangement.","units":{"USD":[{"start":"2021-01-01","end":"2021-03-31","val":487722,"accn":"0001193125-21-173844","fy":2021,"fp":"Q1","form":"10-Q/A","filed":"2021-05-27","frame":"CY2021Q1"},{"start":"2021-01-01","end":"2021-06-30","val":487722,"accn":"0001193125-21-247908","fy":2021,"fp":"Q2","form":"10-Q","filed":"2021-08-16"},{"start":"2021-01-01","end":"2021-09-30","val":487723,"accn":"0001193125-21-334994","fy":2021,"fp":"Q3","form":"10-Q","filed":"2021-11-19"}]}},"TaxesOther":{"label":"Taxes, Other","description":"Amount of tax expense classified as other.","units":{"USD":[{"start":"2021-01-01","end":"2021-06-30","val":100000,"accn":"0001193125-21-247908","fy":2021,"fp":"Q2","form":"10-Q","filed":"2021-08-16"},{"start":"2021-04-01","end":"2021-06-30","val":100000,"accn":"0001193125-21-247908","fy":2021,"fp":"Q2","form":"10-Q","filed":"2021-08-16","frame":"CY2021Q2"},{"start":"2021-01-01","end":"2021-09-30","val":150000,"accn":"0001193125-21-334994","fy":2021,"fp":"Q3","form":"10-Q","filed":"2021-11-19"},{"start":"2021-07-01","end":"2021-09-30","val":50000,"accn":"0001193125-21-334994","fy":2021,"fp":"Q3","form":"10-Q","filed":"2021-11-19","frame":"CY2021Q3"}]}},"TemporaryEquityCarryingAmountAttributableToParent":{"label":"Temporary Equity, Carrying Amount, Attributable to Parent","description":"Carrying amount, attributable to parent, of an entity's issued and outstanding stock which is not included within permanent equity. Temporary equity is a security with redemption features that are outside the control of the issuer, is not classified as an asset or liability in conformity with GAAP, and is not mandatorily redeemable. Includes any type of security that is redeemable at a fixed or determinable price or on a fixed or determinable date or dates, is redeemable at the option of the holder, or has conditions for redemption which are not solely within the control of the issuer. Includes stock with a put option held by an ESOP and stock redeemable by a holder only in the event of a change in control of the issuer.","units":{"USD":[{"end":"2020-12-31","val":0,"accn":"0001193125-21-173844","fy":2021,"fp":"Q1","form":"10-Q/A","filed":"2021-05-27"},{"end":"2020-12-31","val":0,"accn":"0001193125-21-247908","fy":2021,"fp":"Q2","form":"10-Q","filed":"2021-08-16"},{"end":"2020-12-31","val":0,"accn":"0001193125-21-334994","fy":2021,"fp":"Q3","form":"10-Q","filed":"2021-11-19","frame":"CY2020Q4I"},{"end":"2021-03-19","val":151650025,"accn":"0001193125-21-173844","fy":2021,"fp":"Q1","form":"10-Q/A","filed":"2021-05-27"},{"end":"2021-03-31","val":151712812,"accn":"0001193125-21-173844","fy":2021,"fp":"Q1","form":"10-Q/A","filed":"2021-05-27","frame":"CY2021Q1I"},{"end":"2021-06-30","val":153578335,"accn":"0001193125-21-247908","fy":2021,"fp":"Q2","form":"10-Q","filed":"2021-08-16","frame":"CY2021Q2I"},{"end":"2021-09-30","val":175000000,"accn":"0001193125-21-334994","fy":2021,"fp":"Q3","form":"10-Q","filed":"2021-11-19","frame":"CY2021Q3I"}]}},"TemporaryEquityStockIssuedDuringPeriodValueNewIssues":{"label":"Temporary Equity, Stock Issued During Period, Value, New Issues","description":"Value of new stock classified as temporary equity issued during the period.","units":{"USD":[{"start":"2021-01-01","end":"2021-03-31","val":151712812,"accn":"0001193125-21-173844","fy":2021,"fp":"Q1","form":"10-Q/A","filed":"2021-05-27","frame":"CY2021Q1"},{"start":"2021-01-01","end":"2021-06-30","val":151650025,"accn":"0001193125-21-247908","fy":2021,"fp":"Q2","form":"10-Q","filed":"2021-08-16"},{"start":"2021-04-01","end":"2021-06-30","val":1865522,"accn":"0001193125-21-247908","fy":2021,"fp":"Q2","form":"10-Q","filed":"2021-08-16","frame":"CY2021Q2"}]}},"UnrecognizedTaxBenefits":{"label":"Unrecognized Tax Benefits","description":"Amount of unrecognized tax benefits.","units":{"USD":[{"end":"2021-03-31","val":0,"accn":"0001193125-21-173844","fy":2021,"fp":"Q1","form":"10-Q/A","filed":"2021-05-27","frame":"CY2021Q1I"},{"end":"2021-06-30","val":0,"accn":"0001193125-21-247908","fy":2021,"fp":"Q2","form":"10-Q","filed":"2021-08-16","frame":"CY2021Q2I"},{"end":"2021-09-30","val":0,"accn":"0001193125-21-334994","fy":2021,"fp":"Q3","form":"10-Q","filed":"2021-11-19","frame":"CY2021Q3I"}]}},"UnrecognizedTaxBenefitsIncomeTaxPenaltiesAndInterestExpense":{"label":"Unrecognized Tax Benefits, Income Tax Penalties and Interest Expense","description":"Amount of expense for interest on an underpayment of income taxes and penalties related to a tax position claimed or expected to be claimed in the tax return.","units":{"USD":[{"start":"2021-01-01","end":"2021-03-31","val":0,"accn":"0001193125-21-173844","fy":2021,"fp":"Q1","form":"10-Q/A","filed":"2021-05-27","frame":"CY2021Q1"},{"start":"2021-01-01","end":"2021-06-30","val":0,"accn":"0001193125-21-247908","fy":2021,"fp":"Q2","form":"10-Q","filed":"2021-08-16"},{"start":"2021-01-01","end":"2021-09-30","val":150000,"accn":"0001193125-21-334994","fy":2021,"fp":"Q3","form":"10-Q","filed":"2021-11-19"}]}}}}}